nmma/__init__.py
nmma/__pycache__/__init__.cpython-37.pyc
nmma/em/__init__.py
nmma/em/analysis.py
nmma/em/analysis_condor.py
nmma/em/analysis_lbol.py
nmma/em/combine_EOS.py
nmma/em/create_injection_condor.py
nmma/em/create_injection_slurm.py
nmma/em/create_lightcurves.py
nmma/em/create_lightcurves_condor.py
nmma/em/create_lightcurves_slurm.py
nmma/em/create_svdmodel.py
nmma/em/detect_lightcurves.py
nmma/em/gwem_Hubble_estimate.py
nmma/em/gwem_resampling.py
nmma/em/gwem_resampling_condor.py
nmma/em/gwem_resampling_utils.py
nmma/em/gwsamples_creation.py
nmma/em/injection.py
nmma/em/injection_summary.py
nmma/em/io.py
nmma/em/lightcurve_marginalization.py
nmma/em/likelihood.py
nmma/em/manual.py
nmma/em/model.py
nmma/em/model_lbol.py
nmma/em/model_parameters.py
nmma/em/multi_config_analysis.py
nmma/em/prior.py
nmma/em/svdmodel_benchmark.py
nmma/em/systematics.py
nmma/em/training.py
nmma/em/utils.py
nmma/em/utils_lbol.py
nmma/em/validate_lightcurve.py
nmma/em/__pycache__/__init__.cpython-37.pyc
nmma/em/__pycache__/likelihood.cpython-37.pyc
nmma/em/__pycache__/model.cpython-37.pyc
nmma/em/__pycache__/utils.cpython-37.pyc
nmma/em/data/ZTF_revisit_kde_i.joblib
nmma/em/data/ZTF_revisit_kde_public.joblib
nmma/em/data/ZTF_sampling_public.pkl
nmma/em/data/ZTF_uncer_params.pkl
nmma/em/data/__init__.py
nmma/em/data/lims_ToO_180_g.joblib
nmma/em/data/lims_ToO_180_r.joblib
nmma/em/data/lims_ToO_300_g.joblib
nmma/em/data/lims_ToO_300_r.joblib
nmma/em/data/lims_i.joblib
nmma/em/data/lims_public_g.joblib
nmma/em/data/lims_public_r.joblib
nmma/em/data/sampling_ToO_180.pkl
nmma/em/data/sampling_ToO_300.pkl
nmma/em/data/__pycache__/__init__.cpython-38.pyc
nmma/eos/__init__.py
nmma/eos/create_injection.py
nmma/eos/eos.py
nmma/eos/tov.py
nmma/eos/utils.py
nmma/eos/__pycache__/__init__.cpython-37.pyc
nmma/eos/__pycache__/eos.cpython-37.pyc
nmma/eos/__pycache__/tov.cpython-37.pyc
nmma/eos/__pycache__/utils.cpython-37.pyc
nmma/gw/likelihood.py
nmma/joint/__init__.py
nmma/joint/constraints.py
nmma-0.2.3.dist-info/licenses/LICENSE
nmma-0.2.3.dist-info/METADATA
nmma-0.2.3.dist-info/WHEEL
nmma-0.2.3.dist-info/entry_points.txt
nmma-0.2.3.dist-info/top_level.txt
nmma-0.2.3.dist-info/RECORD
