Metadata-Version: 2.4
Name: nmma
Version: 0.2.3
Summary: A nuclear physics multi-messenger Bayesian inference library
Author-email: "Peter Tsun Ho Pang, Michael Coughlin, Tim Dietrich, Ingo Tews" <nuclear_multimessenger_astronomy@googlegroups.com>
License: GPLv3
Project-URL: Homepage, https://github.com/nuclear-multimessenger-astronomy/nmma
Project-URL: Documentation, https://nuclear-multimessenger-astronomy.github.io/nmma/
Project-URL: Download, https://pypi.org/project/nmma/#files
Project-URL: Tracker, https://github.com/nuclear-multimessenger-astronomy/nmma/issues
Classifier: Programming Language :: Python :: 3
Classifier: Programming Language :: Python :: 3.10
Classifier: Programming Language :: Python :: 3.11
Classifier: Programming Language :: Python :: 3.12
Classifier: Programming Language :: Python :: 3.13
Classifier: Intended Audience :: Science/Research
Classifier: Intended Audience :: End Users/Desktop
Classifier: Intended Audience :: Developers
Classifier: Natural Language :: English
Classifier: Topic :: Scientific/Engineering
Classifier: Topic :: Scientific/Engineering :: Astronomy
Classifier: Topic :: Scientific/Engineering :: Physics
Classifier: Operating System :: POSIX
Classifier: Operating System :: Unix
Classifier: Operating System :: MacOS
Classifier: License :: OSI Approved :: GNU General Public License v3 (GPLv3)
Requires-Python: <3.14,>=3.10
License-File: LICENSE
Requires-Dist: future
Requires-Dist: bilby>=2.4.1
Requires-Dist: bilby_pipe==1.5.0
Requires-Dist: colorcet
Requires-Dist: numpy>2.0
Requires-Dist: matplotlib>3.8
Requires-Dist: scipy>=1.10
Requires-Dist: pandas>2.0
Requires-Dist: astropy>=5.3.4
Requires-Dist: pymultinest
Requires-Dist: sncosmo
Requires-Dist: dust_extinction
Requires-Dist: arviz
Requires-Dist: p_tqdm
Requires-Dist: tornado
Requires-Dist: notebook
Requires-Dist: ligo.skymap
Requires-Dist: healpy
Provides-Extra: doc
Requires-Dist: sphinx>=5.0; extra == "doc"
Requires-Dist: sphinx_math_dollar; extra == "doc"
Requires-Dist: recommonmark; extra == "doc"
Requires-Dist: numpydoc; extra == "doc"
Requires-Dist: sphinx-rtd-theme; extra == "doc"
Requires-Dist: notedown; extra == "doc"
Requires-Dist: jsx-lexer; extra == "doc"
Requires-Dist: linkify-it-py; extra == "doc"
Requires-Dist: linkify; extra == "doc"
Requires-Dist: myst-parser; extra == "doc"
Requires-Dist: sphinx-book-theme; extra == "doc"
Requires-Dist: sphinx_copybutton; extra == "doc"
Requires-Dist: sphinx-github-changelog; extra == "doc"
Provides-Extra: grb
Requires-Dist: afterglowpy>=0.7.3; extra == "grb"
Requires-Dist: wrapt_timeout_decorator; extra == "grb"
Provides-Extra: production
Requires-Dist: parallel_bilby>=2.0.2; extra == "production"
Requires-Dist: nestcheck; extra == "production"
Requires-Dist: mpi4py; extra == "production"
Provides-Extra: neuralnet
Requires-Dist: torch; extra == "neuralnet"
Requires-Dist: nflows; extra == "neuralnet"
Requires-Dist: torchvision; extra == "neuralnet"
Provides-Extra: sklearn
Requires-Dist: scikit-learn>=1.0.2; extra == "sklearn"
Provides-Extra: tf
Requires-Dist: tensorflow; extra == "tf"
Provides-Extra: sampler
Requires-Dist: ultranest; extra == "sampler"
Dynamic: license-file
